{
  "account_info": "<AdAccount> {\n    \"account_status\": 1,\n    \"currency\": \"ARS\",\n    \"id\": \"act_111192969640236\",\n    \"name\": \"Colppy\",\n    \"timezone_name\": \"America/Argentina/San_Luis\"\n}",
  "campaigns": [
    {
      "id": "120208481597210374",
      "name": "Integraci\u00f3n Flowint",
      "status": "PAUSED",
      "objective": "OUTCOME_LEADS",
      "created_time": "2024-05-02T17:53:59-0300",
      "updated_time": "2024-05-03T13:23:03-0300",
      "start_time": "2024-05-02T17:54:00-0300",
      "stop_time": "Unknown"
    },
    {
      "id": "120208298131640374",
      "name": "Webinar Mayo",
      "status": "PAUSED",
      "objective": "OUTCOME_LEADS",
      "created_time": "2024-04-22T19:24:53-0300",
      "updated_time": "2024-05-03T13:23:08-0300",
      "start_time": "2024-04-22T19:24:53-0300",
      "stop_time": "2024-05-08T05:30:00-0300"
    },
    {
      "id": "120207633558320374",
      "name": "Leads Referidos",
      "status": "PAUSED",
      "objective": "OUTCOME_LEADS",
      "created_time": "2024-03-30T16:05:25-0300",
      "updated_time": "2024-05-03T13:23:12-0300",
      "start_time": "2024-04-01T00:01:00-0300",
      "stop_time": "2024-04-30T23:59:00-0300"
    },
    {
      "id": "120207589547190374",
      "name": "Leads - 5 errores",
      "status": "PAUSED",
      "objective": "OUTCOME_LEADS",
      "created_time": "2024-03-28T18:08:21-0300",
      "updated_time": "2024-05-03T13:23:10-0300",
      "start_time": "2024-03-28T18:08:22-0300",
      "stop_time": "2024-04-30T23:59:00-0300"
    },
    {
      "id": "120207372784860374",
      "name": "Webinar Abril",
      "status": "PAUSED",
      "objective": "OUTCOME_LEADS",
      "created_time": "2024-03-22T17:06:29-0300",
      "updated_time": "2025-08-12T16:44:43-0300",
      "start_time": "2024-03-22T17:06:30-0300",
      "stop_time": "2024-04-08T23:59:00-0300"
    },
    {
      "id": "120207366349470374",
      "name": "Leads Multimoneda",
      "status": "PAUSED",
      "objective": "OUTCOME_LEADS",
      "created_time": "2024-03-22T16:18:59-0300",
      "updated_time": "2024-05-03T13:23:06-0300",
      "start_time": "2024-03-22T16:19:00-0300",
      "stop_time": "Unknown"
    },
    {
      "id": "120207275644290374",
      "name": "Clientes potenciales",
      "status": "PAUSED",
      "objective": "OUTCOME_LEADS",
      "created_time": "2024-03-20T11:56:07-0300",
      "updated_time": "2024-05-03T13:23:10-0300",
      "start_time": "2024-03-20T11:56:07-0300",
      "stop_time": "Unknown"
    },
    {
      "id": "120206962182210374",
      "name": "Whatsapp Bodegas",
      "status": "PAUSED",
      "objective": "OUTCOME_ENGAGEMENT",
      "created_time": "2024-03-13T10:40:43-0300",
      "updated_time": "2025-08-12T16:44:43-0300",
      "start_time": "2024-03-13T10:40:43-0300",
      "stop_time": "2024-03-29T13:00:00-0300"
    },
    {
      "id": "120206742578820374",
      "name": "Whatsapp Marzo",
      "status": "PAUSED",
      "objective": "OUTCOME_ENGAGEMENT",
      "created_time": "2024-03-08T18:13:10-0300",
      "updated_time": "2025-08-12T16:44:42-0300",
      "start_time": "2024-03-08T18:13:10-0300",
      "stop_time": "2024-03-29T13:00:00-0300"
    },
    {
      "id": "120205832480140374",
      "name": "Leads 29 de Febrero",
      "status": "PAUSED",
      "objective": "OUTCOME_LEADS",
      "created_time": "2024-02-19T18:47:41-0300",
      "updated_time": "2025-08-12T16:44:40-0300",
      "start_time": "2024-02-19T18:47:42-0300",
      "stop_time": "2024-02-29T23:59:55-0300"
    },
    {
      "id": "120205339866760374",
      "name": "Leads Carnaval 2024",
      "status": "PAUSED",
      "objective": "OUTCOME_LEADS",
      "created_time": "2024-02-08T20:40:52-0300",
      "updated_time": "2024-02-09T11:42:11-0300",
      "start_time": "2024-02-08T20:40:53-0300",
      "stop_time": "2024-02-18T23:59:00-0300"
    },
    {
      "id": "120202437827710374",
      "name": "Leads - RMK Web",
      "status": "PAUSED",
      "objective": "OUTCOME_LEADS",
      "created_time": "2023-12-11T17:51:33-0300",
      "updated_time": "2024-05-03T13:23:07-0300",
      "start_time": "2023-12-11T17:51:33-0300",
      "stop_time": "Unknown"
    },
    {
      "id": "23861611072440373",
      "name": "Brand-PostOrg\u00e1nico",
      "status": "ACTIVE",
      "objective": "OUTCOME_AWARENESS",
      "created_time": "2023-10-06T17:33:02-0300",
      "updated_time": "2025-04-20T11:26:09-0300",
      "start_time": "2023-10-06T18:00:10-0300",
      "stop_time": "2023-10-12T23:59:10-0300"
    },
    {
      "id": "23859362922620373",
      "name": "Alcance-Evento-Peque\u00f1oyMedianoProfesional",
      "status": "PAUSED",
      "objective": "OUTCOME_AWARENESS",
      "created_time": "2023-09-22T17:22:06-0300",
      "updated_time": "2023-10-02T09:46:09-0300",
      "start_time": "2023-09-22T17:30:21-0300",
      "stop_time": "2023-09-30T23:59:21-0300"
    },
    {
      "id": "23858917331900373",
      "name": "Leads-WSP-Contadores",
      "status": "PAUSED",
      "objective": "OUTCOME_ENGAGEMENT",
      "created_time": "2023-09-15T15:41:23-0300",
      "updated_time": "2023-10-02T09:47:19-0300",
      "start_time": "2023-09-15T17:00:34-0300",
      "stop_time": "Unknown"
    },
    {
      "id": "23857988564550373",
      "name": "Leads-Landing-Sueldos-Contadores&Empresas",
      "status": "PAUSED",
      "objective": "OUTCOME_LEADS",
      "created_time": "2023-08-31T17:21:09-0300",
      "updated_time": "2024-05-03T13:23:08-0300",
      "start_time": "2023-09-01T07:00:45-0300",
      "stop_time": "Unknown"
    },
    {
      "id": "23857540863210373",
      "name": "Trafico-Magneto-Excel",
      "status": "PAUSED",
      "objective": "OUTCOME_TRAFFIC",
      "created_time": "2023-08-15T16:17:42-0300",
      "updated_time": "2024-03-21T11:46:36-0300",
      "start_time": "2023-08-15T17:00:22-0300",
      "stop_time": "Unknown"
    },
    {
      "id": "23857537127590373",
      "name": "Trafico-Magneto-TiendaOnline",
      "status": "PAUSED",
      "objective": "OUTCOME_TRAFFIC",
      "created_time": "2023-08-15T11:44:47-0300",
      "updated_time": "2024-03-21T11:46:34-0300",
      "start_time": "2023-08-15T13:00:17-0300",
      "stop_time": "Unknown"
    },
    {
      "id": "23857325544650373",
      "name": "WhatsApp-Sueldos-Contadores",
      "status": "PAUSED",
      "objective": "OUTCOME_ENGAGEMENT",
      "created_time": "2023-08-05T16:58:55-0300",
      "updated_time": "2023-08-31T17:24:56-0300",
      "start_time": "2023-08-05T17:30:35-0300",
      "stop_time": "Unknown"
    },
    {
      "id": "23857322300520373",
      "name": "WhatsApp-Sueldos-Empresas",
      "status": "PAUSED",
      "objective": "OUTCOME_ENGAGEMENT",
      "created_time": "2023-08-05T10:38:24-0300",
      "updated_time": "2023-08-31T17:24:57-0300",
      "start_time": "2023-08-05T11:30:58-0300",
      "stop_time": "Unknown"
    },
    {
      "id": "23857104119580373",
      "name": "WSP-Sueldos-Empresas",
      "status": "PAUSED",
      "objective": "OUTCOME_ENGAGEMENT",
      "created_time": "2023-07-28T16:21:52-0300",
      "updated_time": "2023-08-05T10:38:55-0300",
      "start_time": "2023-07-28T16:21:52-0300",
      "stop_time": "Unknown"
    },
    {
      "id": "23857104032220373",
      "name": "WSP-Sueldos-Contadores",
      "status": "PAUSED",
      "objective": "OUTCOME_ENGAGEMENT",
      "created_time": "2023-07-28T16:14:18-0300",
      "updated_time": "2023-08-05T17:00:44-0300",
      "start_time": "2023-07-28T16:14:19-0300",
      "stop_time": "Unknown"
    },
    {
      "id": "23857083988880373",
      "name": "FormLeads-SistemadeGestion-Contadores&Empresas",
      "status": "PAUSED",
      "objective": "OUTCOME_LEADS",
      "created_time": "2023-07-27T18:35:52-0300",
      "updated_time": "2023-09-15T15:42:32-0300",
      "start_time": "2023-07-28T10:00:59-0300",
      "stop_time": "Unknown"
    },
    {
      "id": "23855414072300373",
      "name": "Trafico Directo Home",
      "status": "PAUSED",
      "objective": "OUTCOME_TRAFFIC",
      "created_time": "2023-06-23T15:00:11-0300",
      "updated_time": "2023-07-06T10:40:21-0300",
      "start_time": "2023-06-23T16:00:52-0300",
      "stop_time": "2023-06-30T23:52:52-0300"
    },
    {
      "id": "23854866934730373",
      "name": "Magneto Gu\u00eda para Pymes",
      "status": "PAUSED",
      "objective": "OUTCOME_TRAFFIC",
      "created_time": "2023-06-12T10:41:57-0300",
      "updated_time": "2023-07-11T09:27:12-0300",
      "start_time": "2023-06-12T12:10:18-0300",
      "stop_time": "Unknown"
    },
    {
      "id": "23854209275120373",
      "name": "Evento Firmas y Recibos de Sueldos 23/5",
      "status": "PAUSED",
      "objective": "OUTCOME_TRAFFIC",
      "created_time": "2023-05-16T10:30:18-0300",
      "updated_time": "2023-05-24T15:53:21-0300",
      "start_time": "2023-05-16T11:22:20-0300",
      "stop_time": "2023-05-23T10:00:20-0300"
    },
    {
      "id": "23854189051390373",
      "name": "Plantilla de Ajuste por Inflaci\u00f3n",
      "status": "PAUSED",
      "objective": "OUTCOME_TRAFFIC",
      "created_time": "2023-05-15T16:40:59-0300",
      "updated_time": "2023-07-11T09:29:08-0300",
      "start_time": "2023-05-15T17:00:52-0300",
      "stop_time": "Unknown"
    },
    {
      "id": "23853914025680373",
      "name": "Evento 10/5 | Webinar E-Cheq",
      "status": "PAUSED",
      "objective": "OUTCOME_TRAFFIC",
      "created_time": "2023-04-27T10:26:11-0300",
      "updated_time": "2023-05-15T16:44:38-0300",
      "start_time": "2023-04-27T12:00:54-0300",
      "stop_time": "2023-05-10T12:00:00-0300"
    },
    {
      "id": "23853821842130373",
      "name": "Integraci\u00f3n Sueldos | WhatsApp",
      "status": "PAUSED",
      "objective": "OUTCOME_ENGAGEMENT",
      "created_time": "2023-04-20T16:57:15-0300",
      "updated_time": "2023-08-31T15:44:45-0300",
      "start_time": "2023-04-20T16:57:16-0300",
      "stop_time": "Unknown"
    },
    {
      "id": "23853013054670373",
      "name": "Guia para Pymes",
      "status": "PAUSED",
      "objective": "OUTCOME_TRAFFIC",
      "created_time": "2023-02-13T18:01:36-0300",
      "updated_time": "2023-05-10T16:54:46-0300",
      "start_time": "2023-02-13T18:01:36-0300",
      "stop_time": "Unknown"
    },
    {
      "id": "23852512688030373",
      "name": "Campa\u00f1a Tango BDD",
      "status": "PAUSED",
      "objective": "OUTCOME_LEADS",
      "created_time": "2022-12-23T17:06:53-0300",
      "updated_time": "2023-05-15T15:31:33-0300",
      "start_time": "2022-12-23T17:06:55-0300",
      "stop_time": "Unknown"
    },
    {
      "id": "23852505627950373",
      "name": "Plantilla de Ajuste por Inflaci\u00f3n DIC 2022",
      "status": "PAUSED",
      "objective": "OUTCOME_SALES",
      "created_time": "2022-12-22T20:23:29-0300",
      "updated_time": "2023-03-02T10:39:22-0300",
      "start_time": "2022-12-22T20:23:30-0300",
      "stop_time": "Unknown"
    },
    {
      "id": "23852363948270373",
      "name": "Campa\u00f1a de Navidad",
      "status": "PAUSED",
      "objective": "OUTCOME_TRAFFIC",
      "created_time": "2022-12-07T15:29:02-0300",
      "updated_time": "2025-08-12T16:44:38-0300",
      "start_time": "2022-12-07T15:29:03-0300",
      "stop_time": "2022-12-31T00:00:00-0300"
    },
    {
      "id": "23852249021670373",
      "name": "BlackFriday2022 - Landing mundial",
      "status": "PAUSED",
      "objective": "OUTCOME_TRAFFIC",
      "created_time": "2022-11-25T09:51:04-0300",
      "updated_time": "2025-08-12T16:44:27-0300",
      "start_time": "2022-11-25T09:51:05-0300",
      "stop_time": "2022-11-30T23:00:00-0300"
    },
    {
      "id": "23852216168640373",
      "name": "BlackFriday2022",
      "status": "PAUSED",
      "objective": "OUTCOME_TRAFFIC",
      "created_time": "2022-11-22T14:58:05-0300",
      "updated_time": "2025-08-12T16:44:29-0300",
      "start_time": "2022-11-22T17:00:45-0300",
      "stop_time": "2022-11-30T23:00:00-0300"
    },
    {
      "id": "23852167768570373",
      "name": "Sistema de Gesti\u00f3n | Landing",
      "status": "PAUSED",
      "objective": "CONVERSIONS",
      "created_time": "2022-11-17T13:35:20-0300",
      "updated_time": "2023-08-05T10:11:04-0300",
      "start_time": "2022-11-17T13:35:22-0300",
      "stop_time": "Unknown"
    },
    {
      "id": "23852167186340373",
      "name": "Eventos",
      "status": "PAUSED",
      "objective": "OUTCOME_TRAFFIC",
      "created_time": "2022-11-17T13:03:44-0300",
      "updated_time": "2025-08-12T16:44:36-0300",
      "start_time": "2022-11-17T13:03:46-0300",
      "stop_time": "2022-12-01T12:25:31-0300"
    },
    {
      "id": "23852003026800373",
      "name": "Eventos y Webinar",
      "status": "PAUSED",
      "objective": "OUTCOME_TRAFFIC",
      "created_time": "2022-11-02T17:22:49-0300",
      "updated_time": "2025-08-12T16:44:35-0300",
      "start_time": "2022-11-02T17:22:50-0300",
      "stop_time": "2022-11-09T12:00:00-0300"
    },
    {
      "id": "23851976090800373",
      "name": "Campa\u00f1a RMKT - Tango Campa\u00f1a",
      "status": "PAUSED",
      "objective": "OUTCOME_SALES",
      "created_time": "2022-11-06T09:13:49-0300",
      "updated_time": "2022-12-23T15:15:08-0300",
      "start_time": "2022-11-06T09:13:57-0300",
      "stop_time": "Unknown"
    },
    {
      "id": "23851884652410373",
      "name": "Cybermonday 2022",
      "status": "PAUSED",
      "objective": "OUTCOME_LEADS",
      "created_time": "2022-10-21T16:56:18-0300",
      "updated_time": "2022-11-02T14:51:03-0300",
      "start_time": "2022-10-22T00:00:09-0300",
      "stop_time": "2022-11-02T00:00:00-0300"
    },
    {
      "id": "23851563874290373",
      "name": "(Conversi\u00f3n) Gesti\u00f3n del Tiempo -Ebook V.2",
      "status": "PAUSED",
      "objective": "CONVERSIONS",
      "created_time": "2022-09-23T15:37:33-0300",
      "updated_time": "2023-01-13T09:40:13-0300",
      "start_time": "2022-09-23T15:37:34-0300",
      "stop_time": "Unknown"
    },
    {
      "id": "23851363271010373",
      "name": "Masterclass - Federico Pantanetti",
      "status": "PAUSED",
      "objective": "OUTCOME_TRAFFIC",
      "created_time": "2022-08-31T22:48:22-0300",
      "updated_time": "2022-11-02T14:55:42-0300",
      "start_time": "2022-09-08T09:00:01-0300",
      "stop_time": "2022-09-21T12:00:01-0300"
    },
    {
      "id": "23851173244040373",
      "name": "Cumple Colppy 12 a\u00f1os - Conversi\u00f3n",
      "status": "PAUSED",
      "objective": "OUTCOME_SALES",
      "created_time": "2022-08-12T13:46:04-0300",
      "updated_time": "2022-09-15T14:47:17-0300",
      "start_time": "2022-08-12T13:46:04-0300",
      "stop_time": "2022-08-20T23:33:57-0300"
    },
    {
      "id": "23851104772900373",
      "name": "Interacci\u00f3n Posteos",
      "status": "PAUSED",
      "objective": "OUTCOME_ENGAGEMENT",
      "created_time": "2022-08-02T15:15:31-0300",
      "updated_time": "2023-04-20T16:30:19-0300",
      "start_time": "2022-08-02T15:15:31-0300",
      "stop_time": "Unknown"
    },
    {
      "id": "23851065685840373",
      "name": "Evento: Masterclass",
      "status": "PAUSED",
      "objective": "OUTCOME_TRAFFIC",
      "created_time": "2022-07-28T17:01:01-0300",
      "updated_time": "2022-11-02T14:55:47-0300",
      "start_time": "2022-07-28T18:00:32-0300",
      "stop_time": "2022-08-09T12:00:32-0300"
    },
    {
      "id": "23850987895380373",
      "name": "Promo d\u00eda del amigo - Tr\u00e1fico",
      "status": "PAUSED",
      "objective": "OUTCOME_TRAFFIC",
      "created_time": "2022-07-19T17:02:42-0300",
      "updated_time": "2022-11-02T14:55:56-0300",
      "start_time": "2022-07-19T18:00:11-0300",
      "stop_time": "2022-07-21T09:00:11-0300"
    },
    {
      "id": "23850747166100373",
      "name": "Evento: Semana de las PyMEs",
      "status": "PAUSED",
      "objective": "EVENT_RESPONSES",
      "created_time": "2022-06-21T16:38:54-0300",
      "updated_time": "2022-06-26T19:08:09-0300",
      "start_time": "2022-06-21T16:39:24-0300",
      "stop_time": "2022-06-24T16:39:24-0300"
    },
    {
      "id": "23850716279050373",
      "name": "Campa\u00f1as de conversi\u00f3n Entropia - Ciclo de Charlas Campa\u00f1a",
      "status": "PAUSED",
      "objective": "CONVERSIONS",
      "created_time": "2022-06-17T18:15:38-0300",
      "updated_time": "2022-11-02T14:55:56-0300",
      "start_time": "2022-06-17T18:30:12-0300",
      "stop_time": "2022-06-23T14:00:00-0300"
    },
    {
      "id": "23850687883640373",
      "name": "Evento semana de las Pymes - Conversi\u00f3n",
      "status": "PAUSED",
      "objective": "CONVERSIONS",
      "created_time": "2022-06-14T14:36:10-0300",
      "updated_time": "2022-06-26T19:08:17-0300",
      "start_time": "2022-06-14T16:00:20-0300",
      "stop_time": "2022-06-21T12:00:00-0300"
    },
    {
      "id": "23850546842320373",
      "name": "Tr\u00e1fico Hot Sale 2022",
      "status": "PAUSED",
      "objective": "LINK_CLICKS",
      "created_time": "2022-05-27T10:18:34-0300",
      "updated_time": "2022-11-02T14:55:53-0300",
      "start_time": "2022-05-27T10:30:15-0300",
      "stop_time": "2022-05-31T23:30:15-0300"
    },
    {
      "id": "23850240933180373",
      "name": "Sistema de Gesti\u00f3n - Mensajes a WhatsApp",
      "status": "PAUSED",
      "objective": "MESSAGES",
      "created_time": "2022-04-21T19:51:29-0300",
      "updated_time": "2023-05-15T16:51:25-0300",
      "start_time": "2022-04-21T21:00:22-0300",
      "stop_time": "2023-05-31T23:30:00-0300"
    },
    {
      "id": "23850003843370373",
      "name": "Gesti\u00f3n del Tiempo - Conversi\u00f3n",
      "status": "PAUSED",
      "objective": "CONVERSIONS",
      "created_time": "2022-03-22T14:35:38-0300",
      "updated_time": "2022-09-26T09:12:28-0300",
      "start_time": "2022-03-22T15:00:54-0300",
      "stop_time": "Unknown"
    },
    {
      "id": "23849978304460373",
      "name": "Ecommerce | Landing",
      "status": "PAUSED",
      "objective": "CONVERSIONS",
      "created_time": "2022-03-19T09:09:04-0300",
      "updated_time": "2023-08-03T09:16:46-0300",
      "start_time": "2022-03-19T10:00:19-0300",
      "stop_time": "Unknown"
    },
    {
      "id": "23849873696380373",
      "name": "Evento Criptomonedas - Conversi\u00f3n",
      "status": "PAUSED",
      "objective": "CONVERSIONS",
      "created_time": "2022-03-07T16:27:42-0300",
      "updated_time": "2022-03-15T09:53:46-0300",
      "start_time": "2022-03-07T17:00:03-0300",
      "stop_time": "2022-03-16T11:00:00-0300"
    },
    {
      "id": "23849768043940373",
      "name": "Reproducciones de video - Cierre contable",
      "status": "PAUSED",
      "objective": "VIDEO_VIEWS",
      "created_time": "2022-02-21T08:07:23-0300",
      "updated_time": "2022-05-24T10:11:22-0300",
      "start_time": "2022-02-21T08:07:24-0300",
      "stop_time": "Unknown"
    },
    {
      "id": "23849724367840373",
      "name": "Campa\u00f1a Branding Colppy | Reconocimiento de Marca | - Copia",
      "status": "PAUSED",
      "objective": "BRAND_AWARENESS",
      "created_time": "2022-02-15T16:25:38-0300",
      "updated_time": "2023-03-02T10:39:28-0300",
      "start_time": "2022-02-15T16:25:38-0300",
      "stop_time": "Unknown"
    },
    {
      "id": "23849721079350373",
      "name": "Reconocimiento de marca - Copia",
      "status": "PAUSED",
      "objective": "LEAD_GENERATION",
      "created_time": "2022-06-21T11:23:53-0300",
      "updated_time": "2022-06-21T11:23:53-0300",
      "start_time": "2022-10-06T11:15:25-0300",
      "stop_time": "Unknown"
    },
    {
      "id": "23849606420130373",
      "name": "Sistema de Gesti\u00f3n - Conversi\u00f3n",
      "status": "PAUSED",
      "objective": "CONVERSIONS",
      "created_time": "2022-02-01T16:22:36-0300",
      "updated_time": "2022-11-23T10:22:14-0300",
      "start_time": "2022-02-01T16:22:37-0300",
      "stop_time": "Unknown"
    },
    {
      "id": "23849574421500373",
      "name": "Ajuste Inflaci\u00f3n IG - Conversi\u00f3n",
      "status": "PAUSED",
      "objective": "CONVERSIONS",
      "created_time": "2022-01-28T11:00:30-0300",
      "updated_time": "2022-03-22T14:10:23-0300",
      "start_time": "2022-01-28T11:05:01-0300",
      "stop_time": "Unknown"
    },
    {
      "id": "23849406383310373",
      "name": "Ajuste Inflaci\u00f3n IG - Tr\u00e1fico",
      "status": "PAUSED",
      "objective": "LINK_CLICKS",
      "created_time": "2022-01-06T12:36:15-0300",
      "updated_time": "2022-10-13T16:08:16-0300",
      "start_time": "2022-01-06T13:00:57-0300",
      "stop_time": "2022-07-18T13:00:57-0300"
    },
    {
      "id": "23849295522520373",
      "name": "Campa\u00f1a Branding Colppy RRSS | Tr\u00e1fico BLOG",
      "status": "PAUSED",
      "objective": "LINK_CLICKS",
      "created_time": "2022-02-09T10:42:46-0300",
      "updated_time": "2022-11-02T14:56:55-0300",
      "start_time": "2022-02-09T15:52:36-0300",
      "stop_time": "2022-03-31T00:00:00-0300"
    },
    {
      "id": "23849278079930373",
      "name": "Campa\u00f1a Branding Colppy | Reconocimiento de Marca |",
      "status": "PAUSED",
      "objective": "BRAND_AWARENESS",
      "created_time": "2021-12-20T15:54:04-0300",
      "updated_time": "2022-02-15T16:23:51-0300",
      "start_time": "2021-12-20T16:58:36-0300",
      "stop_time": "Unknown"
    },
    {
      "id": "23849200611690373",
      "name": "Navidad 2021 - Conversiones",
      "status": "PAUSED",
      "objective": "CONVERSIONS",
      "created_time": "2021-12-08T08:11:02-0300",
      "updated_time": "2021-12-27T12:50:03-0300",
      "start_time": "2021-12-09T08:00:57-0300",
      "stop_time": "2021-12-31T23:51:57-0300"
    },
    {
      "id": "23849141368600373",
      "name": "Publicaci\u00f3n: \"Mediante Colppy vas a lograr ordenar las cuentas...\"",
      "status": "PAUSED",
      "objective": "MESSAGES",
      "created_time": "2021-11-30T18:48:49-0300",
      "updated_time": "2021-12-01T09:09:37-0300",
      "start_time": "2021-11-30T18:49:19-0300",
      "stop_time": "2021-12-15T18:49:19-0300"
    },
    {
      "id": "23849084880610373",
      "name": "Libro de Sueldos - Conversi\u00f3n",
      "status": "PAUSED",
      "objective": "CONVERSIONS",
      "created_time": "2021-11-23T15:46:33-0300",
      "updated_time": "2022-06-07T10:36:28-0300",
      "start_time": "2021-11-23T16:00:21-0300",
      "stop_time": "Unknown"
    },
    {
      "id": "23849054167720373",
      "name": "Black Friday 2021",
      "status": "PAUSED",
      "objective": "CONVERSIONS",
      "created_time": "2021-11-19T18:48:56-0300",
      "updated_time": "2022-02-15T11:25:25-0300",
      "start_time": "2021-11-23T08:00:52-0300",
      "stop_time": "2021-11-30T23:30:52-0300"
    },
    {
      "id": "23849053627760373",
      "name": "Libro de Sueldos Reel IG",
      "status": "PAUSED",
      "objective": "REACH",
      "created_time": "2021-11-19T17:29:08-0300",
      "updated_time": "2021-11-24T09:27:46-0300",
      "start_time": "2021-11-19T18:00:40-0300",
      "stop_time": "2021-11-25T10:00:37-0300"
    },
    {
      "id": "23849053495520373",
      "name": "Evento: Libro de Sueldos Digital",
      "status": "PAUSED",
      "objective": "EVENT_RESPONSES",
      "created_time": "2021-11-19T16:33:13-0300",
      "updated_time": "2021-11-24T09:27:42-0300",
      "start_time": "2021-11-19T16:33:43-0300",
      "stop_time": "2021-11-24T16:33:43-0300"
    },
    {
      "id": "23848893634840373",
      "name": "Cyber Monday 21",
      "status": "PAUSED",
      "objective": "LINK_CLICKS",
      "created_time": "2021-11-01T13:05:59-0300",
      "updated_time": "2022-02-15T11:25:31-0300",
      "start_time": "2021-11-01T13:30:58-0300",
      "stop_time": "2021-11-05T23:55:58-0300"
    },
    {
      "id": "23848615426060373",
      "name": "Reconocimiento de marca",
      "status": "PAUSED",
      "objective": "LINK_CLICKS",
      "created_time": "2021-10-01T13:05:07-0300",
      "updated_time": "2022-02-16T12:43:29-0300",
      "start_time": "2021-10-01T13:05:08-0300",
      "stop_time": "Unknown"
    },
    {
      "id": "23848597427640373",
      "name": "Publicaci\u00f3n: \"Colppy es tu aliado N\u00ba1 para todas las etapas del...\"",
      "status": "PAUSED",
      "objective": "POST_ENGAGEMENT",
      "created_time": "2021-09-29T18:34:45-0300",
      "updated_time": "2021-10-01T10:00:49-0300",
      "start_time": "2021-09-29T18:34:52-0300",
      "stop_time": "2021-10-04T18:34:45-0300"
    },
    {
      "id": "23848520992890373",
      "name": "Publicaci\u00f3n: \"\u00bfSab\u00edas que Colppy es el \u00fanico sistema que te...\"",
      "status": "PAUSED",
      "objective": "POST_ENGAGEMENT",
      "created_time": "2021-09-20T19:24:07-0300",
      "updated_time": "2021-10-01T15:13:59-0300",
      "start_time": "2021-09-20T19:24:13-0300",
      "stop_time": "2021-09-25T19:24:07-0300"
    },
    {
      "id": "23848479445040373",
      "name": "Publicaci\u00f3n: \"Te presentamos un BENEFICIO pensado para vos:\"",
      "status": "PAUSED",
      "objective": "LINK_CLICKS",
      "created_time": "2021-09-15T15:53:32-0300",
      "updated_time": "2022-02-15T11:25:33-0300",
      "start_time": "2021-09-15T15:53:51-0300",
      "stop_time": "2021-09-20T15:53:32-0300"
    },
    {
      "id": "23848471381500373",
      "name": "Publicaci\u00f3n: \"Te presentamos un BENEFICIO pensado para vos:\"",
      "status": "PAUSED",
      "objective": "LINK_CLICKS",
      "created_time": "2021-09-14T19:34:28-0300",
      "updated_time": "2022-02-15T11:25:33-0300",
      "start_time": "2021-09-14T19:34:32-0300",
      "stop_time": "2021-09-19T19:34:28-0300"
    },
    {
      "id": "23848399215320373",
      "name": "Publicaci\u00f3n: \"Hoy tenemos algo para mostrarte:\"",
      "status": "PAUSED",
      "objective": "LINK_CLICKS",
      "created_time": "2021-09-06T15:32:45-0300",
      "updated_time": "2022-02-15T11:25:34-0300",
      "start_time": "2021-09-06T15:32:50-0300",
      "stop_time": "2021-09-11T15:32:45-0300"
    },
    {
      "id": "23848285538070373",
      "name": "Publicaci\u00f3n: \"Con Colppy pod\u00e9s ganar \ud83d\udcb5 $5.000. Por cada cliente...\"",
      "status": "PAUSED",
      "objective": "LINK_CLICKS",
      "created_time": "2021-08-24T13:37:37-0300",
      "updated_time": "2022-02-15T11:25:35-0300",
      "start_time": "2021-08-24T13:37:43-0300",
      "stop_time": "2021-08-29T13:37:37-0300"
    },
    {
      "id": "23848246795710373",
      "name": "Publicaci\u00f3n: \"El Programa de Formaci\u00f3n de Colppy para...\"",
      "status": "PAUSED",
      "objective": "LINK_CLICKS",
      "created_time": "2021-08-19T11:06:06-0300",
      "updated_time": "2022-02-15T11:25:38-0300",
      "start_time": "2021-08-19T11:06:11-0300",
      "stop_time": "2021-08-24T11:06:06-0300"
    },
    {
      "id": "23848204849250373",
      "name": "Publicaci\u00f3n: \"\ud83c\udf89\ud83c\udf89 Celebramos nuestro #cumpleColppy con...\"",
      "status": "PAUSED",
      "objective": "LINK_CLICKS",
      "created_time": "2021-08-13T15:27:41-0300",
      "updated_time": "2022-02-15T11:26:10-0300",
      "start_time": "2021-08-13T15:27:43-0300",
      "stop_time": "2021-08-20T15:27:41-0300"
    },
    {
      "id": "23848204660470373",
      "name": "Publicaci\u00f3n: \"\ud83c\udf89\ud83c\udf89 Celebramos nuestro #cumpleColppy con...\"",
      "status": "PAUSED",
      "objective": "LINK_CLICKS",
      "created_time": "2021-08-13T15:07:58-0300",
      "updated_time": "2022-02-15T11:26:13-0300",
      "start_time": "2021-08-13T15:08:00-0300",
      "stop_time": "2021-08-20T15:07:58-0300"
    },
    {
      "id": "23848180546780373",
      "name": "Publicaci\u00f3n: \"Colppy Plus te ofrece un sistema de gesti\u00f3n + un...\"",
      "status": "PAUSED",
      "objective": "POST_ENGAGEMENT",
      "created_time": "2021-08-10T14:00:02-0300",
      "updated_time": "2022-02-15T11:26:18-0300",
      "start_time": "2021-08-10T14:00:06-0300",
      "stop_time": "2021-08-15T14:00:02-0300"
    },
    {
      "id": "23848134943700373",
      "name": "Publicaci\u00f3n: \"La clave para lograr la \ud835\ude01\ud835\uddff\ud835\uddee\ud835\uddfb\ud835\ude00\ud835\uddf3\ud835\uddfc\ud835\uddff\ud835\uddfa\ud835\uddee\ud835\uddf0\ud835\uddf6\u00f3\ud835\uddfb \ud835\uddf1\ud835\uddf6\ud835\uddf4\ud835\uddf6\ud835\ude01\ud835\uddee\ud835\uddf9 en...\"",
      "status": "PAUSED",
      "objective": "LINK_CLICKS",
      "created_time": "2021-08-03T16:23:46-0300",
      "updated_time": "2022-02-15T11:26:26-0300",
      "start_time": "2021-08-03T16:23:53-0300",
      "stop_time": "2021-08-08T16:23:46-0300"
    },
    {
      "id": "23848133612780373",
      "name": "INTERACCI\u00d3N - ME GUSTA - AGOSTO 21",
      "status": "PAUSED",
      "objective": "PAGE_LIKES",
      "created_time": "2021-08-03T11:50:40-0300",
      "updated_time": "2022-02-15T11:26:21-0300",
      "start_time": "2021-08-04T09:00:39-0300",
      "stop_time": "2021-08-27T20:00:39-0300"
    },
    {
      "id": "23848105772460373",
      "name": "Publicaci\u00f3n: \"\u00bfTen\u00e9s un negocio o un e-commerce? \u00bfTen\u00e9s la...\"",
      "status": "PAUSED",
      "objective": "POST_ENGAGEMENT",
      "created_time": "2021-07-29T16:54:03-0300",
      "updated_time": "2022-02-15T11:26:22-0300",
      "start_time": "2021-07-29T16:54:09-0300",
      "stop_time": "2021-08-01T16:54:03-0300"
    },
    {
      "id": "23848044240050373",
      "name": "Publicaci\u00f3n: \"\u00a1\ud835\uddd9\ud835\uddd8\ud835\udddf\ud835\udddc\ud835\udded \ud835\uddd7\u00cd\ud835\uddd4 \ud835\uddd7\ud835\uddd8\ud835\udddf \ud835\uddd4\ud835\udde0\ud835\udddc\ud835\uddda\ud835\udde2! En este d\u00eda tan especial,...\"",
      "status": "PAUSED",
      "objective": "LINK_CLICKS",
      "created_time": "2021-07-20T16:14:04-0300",
      "updated_time": "2022-02-15T11:26:24-0300",
      "start_time": "2021-07-20T16:14:09-0300",
      "stop_time": "2021-07-25T16:14:04-0300"
    },
    {
      "id": "23847982884880373",
      "name": "Publicaci\u00f3n: \"Colppy ofrece un sistema de gesti\u00f3n integral con...\"",
      "status": "PAUSED",
      "objective": "POST_ENGAGEMENT",
      "created_time": "2021-07-11T20:05:46-0300",
      "updated_time": "2022-02-15T11:26:07-0300",
      "start_time": "2021-07-11T20:05:50-0300",
      "stop_time": "2021-07-16T20:05:46-0300"
    },
    {
      "id": "23847959201250373",
      "name": "INTERACCI\u00d3N - ME GUSTA - JULIO 21",
      "status": "PAUSED",
      "objective": "PAGE_LIKES",
      "created_time": "2021-07-08T14:37:50-0300",
      "updated_time": "2022-02-15T11:26:25-0300",
      "start_time": "2021-07-09T08:00:13-0300",
      "stop_time": "2021-07-31T00:00:28-0300"
    },
    {
      "id": "23847934989030373",
      "name": "Publicaci\u00f3n: \"\u1d07\u029f \ua731\u1d07\u1d04\u0280\u1d07\u1d1b\u1d0f \u1d05\u1d07\u029f \u00c9x\u026a\u1d1b\u1d0f \ud83c\udfc6 radica en entender que los...\"",
      "status": "PAUSED",
      "objective": "LINK_CLICKS",
      "created_time": "2021-07-05T20:47:29-0300",
      "updated_time": "2022-02-15T11:26:03-0300",
      "start_time": "2021-07-05T20:47:33-0300",
      "stop_time": "2021-07-10T20:47:29-0300"
    },
    {
      "id": "23847878419120373",
      "name": "Publicaci\u00f3n: \"Con Colppy pod\u00e9s ganar $5.000. No te pierdas esta...\"",
      "status": "PAUSED",
      "objective": "LINK_CLICKS",
      "created_time": "2021-06-27T16:34:23-0300",
      "updated_time": "2022-02-15T11:26:05-0300",
      "start_time": "2021-06-27T16:34:27-0300",
      "stop_time": "2021-07-02T16:34:23-0300"
    },
    {
      "id": "23847860814270373",
      "name": "Publicaci\u00f3n: \"Facturar nunca fue m\u00e1s f\u00e1cil. \u00bfConoc\u00e9s el...\"",
      "status": "PAUSED",
      "objective": "LINK_CLICKS",
      "created_time": "2021-06-24T14:16:29-0300",
      "updated_time": "2022-02-15T11:25:58-0300",
      "start_time": "2021-06-24T14:16:34-0300",
      "stop_time": "2021-06-29T14:16:29-0300"
    },
    {
      "id": "23847800717480373",
      "name": "Publicaci\u00f3n: \"\ud835\udc02\ud835\udc28\ud835\udc25\ud835\udc29\ud835\udc29\ud835\udc32 \ud835\udc1e\ud835\udc2c \ud835\udc2d\ud835\udc2e \ud835\udc1a\ud835\udc25\ud835\udc22\ud835\udc1a\ud835\udc1d\ud835\udc28 \ud835\udc0d\u00ba\ud835\udfcf para todas las etapas del...\"",
      "status": "PAUSED",
      "objective": "POST_ENGAGEMENT",
      "created_time": "2021-06-15T15:08:53-0300",
      "updated_time": "2022-02-15T11:26:00-0300",
      "start_time": "2021-06-15T15:08:58-0300",
      "stop_time": "2021-06-20T15:08:53-0300"
    },
    {
      "id": "23847749052040373",
      "name": "Publicaci\u00f3n: \"En esta oportunidad nuestro cliente, el \ud835\ude74\ud835\ude9c\ud835\ude9d\ud835\ude9e\ud835\ude8d\ud835\ude92\ud835\ude98...\"",
      "status": "PAUSED",
      "objective": "LINK_CLICKS",
      "created_time": "2021-06-07T20:51:27-0300",
      "updated_time": "2022-02-15T11:25:55-0300",
      "start_time": "2021-06-07T20:51:34-0300",
      "stop_time": "2021-06-12T20:51:27-0300"
    },
    {
      "id": "23847691059100373",
      "name": "Publicaci\u00f3n: \"Los dichos populares muchas veces nos transmiten...\"",
      "status": "PAUSED",
      "objective": "LINK_CLICKS",
      "created_time": "2021-05-28T19:13:50-0300",
      "updated_time": "2022-02-15T11:25:53-0300",
      "start_time": "2021-05-28T19:13:58-0300",
      "stop_time": "2021-05-31T19:13:50-0300"
    },
    {
      "id": "23847603012930373",
      "name": "Publicaci\u00f3n: \"\ud835\ude4e\ud835\ude64\ud835\ude61\ud835\ude6a\ud835\ude58\ud835\ude5e\ud835\ude64\ud835\ude63\ud835\ude5a\ud835\ude68 \ud835\ude5e\ud835\ude63\ud835\ude63\ud835\ude64\ud835\ude6b\ud835\ude56\ud835\ude59\ud835\ude64\ud835\ude67\ud835\ude56\ud835\ude68 para tu empresa. Hoy en...\"",
      "status": "PAUSED",
      "objective": "POST_ENGAGEMENT",
      "created_time": "2021-05-17T09:02:19-0300",
      "updated_time": "2022-02-15T11:25:51-0300",
      "start_time": "2021-05-17T09:02:32-0300",
      "stop_time": "2021-05-21T09:02:19-0300"
    },
    {
      "id": "23847575028070373",
      "name": "Publicaci\u00f3n: \"Colppy premia a sus mejores clientes, con un...\"",
      "status": "PAUSED",
      "objective": "LINK_CLICKS",
      "created_time": "2021-05-12T11:26:48-0300",
      "updated_time": "2022-02-15T11:25:49-0300",
      "start_time": "2021-05-12T11:26:56-0300",
      "stop_time": "2021-05-16T11:26:48-0300"
    },
    {
      "id": "23847538551520373",
      "name": "Publicaci\u00f3n: \"Aprovech\u00e1 nuestra oferta \ud83d\udd25 por tiempo limitado....\"",
      "status": "PAUSED",
      "objective": "POST_ENGAGEMENT",
      "created_time": "2021-05-06T17:19:30-0300",
      "updated_time": "2022-02-15T11:25:47-0300",
      "start_time": "2021-05-06T17:19:37-0300",
      "stop_time": "2021-05-11T17:19:30-0300"
    },
    {
      "id": "23847373502770373",
      "name": "[Okey] AdFijo-Contadores / Conversiones",
      "status": "PAUSED",
      "objective": "CONVERSIONS",
      "created_time": "2021-04-13T14:49:17-0300",
      "updated_time": "2021-07-26T05:07:32-0300",
      "start_time": "2021-04-13T15:00:57-0300",
      "stop_time": "2021-04-30T23:55:57-0300"
    },
    {
      "id": "23847334532990373",
      "name": "[Okey] Video-Contadores / LEADS",
      "status": "PAUSED",
      "objective": "LEAD_GENERATION",
      "created_time": "2021-04-08T10:49:57-0300",
      "updated_time": "2021-07-26T05:07:32-0300",
      "start_time": "2021-04-08T10:49:59-0300",
      "stop_time": "2021-05-31T23:55:07-0300"
    },
    {
      "id": "23847310853100373",
      "name": "[Okey] AdFijo-Empresas / LEADS",
      "status": "PAUSED",
      "objective": "LEAD_GENERATION",
      "created_time": "2021-04-05T16:01:17-0300",
      "updated_time": "2021-07-26T04:46:47-0300",
      "start_time": "2021-04-05T16:30:59-0300",
      "stop_time": "2021-05-31T23:55:59-0300"
    },
    {
      "id": "23847309965480373",
      "name": "[Okey] AdFijo-Contadores / LEADS",
      "status": "PAUSED",
      "objective": "LEAD_GENERATION",
      "created_time": "2021-04-05T13:28:26-0300",
      "updated_time": "2021-07-26T04:46:47-0300",
      "start_time": "2021-04-05T13:28:27-0300",
      "stop_time": "2021-04-30T23:00:57-0300"
    },
    {
      "id": "23847309106690373",
      "name": "[Okey] Carrusel-Contadores / LEADS",
      "status": "PAUSED",
      "objective": "LEAD_GENERATION",
      "created_time": "2021-04-05T12:59:44-0300",
      "updated_time": "2021-07-26T04:46:47-0300",
      "start_time": "2021-04-05T12:59:46-0300",
      "stop_time": "2021-04-30T23:00:57-0300"
    },
    {
      "id": "23847287547070373",
      "name": "[Okey] AdFijo-Contadores / ClickToSite",
      "status": "PAUSED",
      "objective": "LINK_CLICKS",
      "created_time": "2021-04-01T12:54:30-0300",
      "updated_time": "2021-07-26T04:39:37-0300",
      "start_time": "2021-04-01T14:31:54-0300",
      "stop_time": "2021-04-30T23:00:54-0300"
    },
    {
      "id": "23847287498960373",
      "name": "[Okey] AdFijo-Contadores / WhatsApp",
      "status": "PAUSED",
      "objective": "MESSAGES",
      "created_time": "2021-04-01T12:27:52-0300",
      "updated_time": "2021-07-26T04:39:37-0300",
      "start_time": "2021-04-01T12:27:54-0300",
      "stop_time": "2021-04-30T00:00:00-0300"
    },
    {
      "id": "23847002397410373",
      "name": "Capacitaci\u00f3n de sueldos",
      "status": "PAUSED",
      "objective": "CONVERSIONS",
      "created_time": "2021-02-22T18:35:27-0300",
      "updated_time": "2021-07-26T02:56:56-0300",
      "start_time": "2021-02-23T07:00:49-0300",
      "stop_time": "2021-03-02T16:00:49-0300"
    },
    {
      "id": "23846972597120373",
      "name": "Promo: Volvi\u00f3 la promo verano Contadores",
      "status": "PAUSED",
      "objective": "CONVERSIONS",
      "created_time": "2021-02-17T15:04:07-0300",
      "updated_time": "2021-07-26T02:46:12-0300",
      "start_time": "2021-02-17T15:30:52-0300",
      "stop_time": "2021-02-26T15:00:52-0300"
    },
    {
      "id": "23846972182120373",
      "name": "Promo: Volvi\u00f3 la promo verano pymes",
      "status": "PAUSED",
      "objective": "CONVERSIONS",
      "created_time": "2021-02-17T14:46:59-0300",
      "updated_time": "2021-07-26T02:46:12-0300",
      "start_time": "2021-02-17T15:30:52-0300",
      "stop_time": "2021-02-26T15:00:52-0300"
    },
    {
      "id": "23846403850130373",
      "name": "Promo Navidad",
      "status": "PAUSED",
      "objective": "CONVERSIONS",
      "created_time": "2020-12-11T13:31:52-0300",
      "updated_time": "2021-01-03T11:14:10-0300",
      "start_time": "2020-12-11T13:31:54-0300",
      "stop_time": "Unknown"
    },
    {
      "id": "23846299199800373",
      "name": "Black Friday",
      "status": "PAUSED",
      "objective": "CONVERSIONS",
      "created_time": "2020-11-27T09:29:25-0300",
      "updated_time": "2021-07-25T23:35:41-0300",
      "start_time": "2020-11-27T09:30:15-0300",
      "stop_time": "2020-11-30T18:00:00-0300"
    },
    {
      "id": "23846128113840373",
      "name": "programa-agentes",
      "status": "PAUSED",
      "objective": "CONVERSIONS",
      "created_time": "2020-11-03T10:56:36-0300",
      "updated_time": "2020-12-01T11:50:51-0300",
      "start_time": "2020-11-03T10:56:37-0300",
      "stop_time": "Unknown"
    },
    {
      "id": "23845800330380373",
      "name": "referidos-sep2020",
      "status": "PAUSED",
      "objective": "CONVERSIONS",
      "created_time": "2020-09-24T09:06:49-0300",
      "updated_time": "2022-02-15T11:25:45-0300",
      "start_time": "2020-09-24T09:06:50-0300",
      "stop_time": "2020-09-30T23:59:00-0300"
    },
    {
      "id": "23845634587460373",
      "name": "pymes-generica",
      "status": "PAUSED",
      "objective": "CONVERSIONS",
      "created_time": "2020-09-10T12:56:31-0300",
      "updated_time": "2020-10-08T16:29:10-0300",
      "start_time": "2020-09-10T12:56:32-0300",
      "stop_time": "Unknown"
    },
    {
      "id": "23845148259980373",
      "name": "Programa-formacion-cursos-contadores",
      "status": "PAUSED",
      "objective": "LINK_CLICKS",
      "created_time": "2020-07-06T13:28:55-0300",
      "updated_time": "2021-07-25T14:41:23-0300",
      "start_time": "2020-07-06T13:28:56-0300",
      "stop_time": "2020-08-20T13:59:50-0300"
    },
    {
      "id": "23845037515290373",
      "name": "descargable-ebook-ecommerce",
      "status": "PAUSED",
      "objective": "LINK_CLICKS",
      "created_time": "2020-06-16T15:42:19-0300",
      "updated_time": "2020-11-03T10:36:07-0300",
      "start_time": "2020-06-16T15:42:20-0300",
      "stop_time": "Unknown"
    },
    {
      "id": "23844688169420373",
      "name": "descargable-liquidaci\u00f3n-sueldos",
      "status": "PAUSED",
      "objective": "CONVERSIONS",
      "created_time": "2020-04-30T13:27:37-0300",
      "updated_time": "2020-12-10T11:40:01-0300",
      "start_time": "2020-04-30T13:27:38-0300",
      "stop_time": "Unknown"
    },
    {
      "id": "23844688130460373",
      "name": "descargable-ajuste-por-inflaci\u00f3n",
      "status": "PAUSED",
      "objective": "CONVERSIONS",
      "created_time": "2020-04-30T13:13:16-0300",
      "updated_time": "2020-12-10T11:39:58-0300",
      "start_time": "2020-04-30T13:13:18-0300",
      "stop_time": "Unknown"
    },
    {
      "id": "23844680492890373",
      "name": "Colppy-Plus",
      "status": "PAUSED",
      "objective": "CONVERSIONS",
      "created_time": "2020-04-29T17:29:16-0300",
      "updated_time": "2020-08-07T15:53:22-0300",
      "start_time": "2020-04-29T17:29:18-0300",
      "stop_time": "Unknown"
    },
    {
      "id": "23844664271070373",
      "name": "Programa-formacion-contadores",
      "status": "PAUSED",
      "objective": "LINK_CLICKS",
      "created_time": "2020-04-28T12:52:01-0300",
      "updated_time": "2020-08-06T10:41:53-0300",
      "start_time": "2020-04-28T12:52:04-0300",
      "stop_time": "Unknown"
    },
    {
      "id": "23844664128650373",
      "name": "Programa-formacion-pymes",
      "status": "PAUSED",
      "objective": "LINK_CLICKS",
      "created_time": "2020-04-28T12:07:04-0300",
      "updated_time": "2020-08-06T10:41:55-0300",
      "start_time": "2020-04-28T12:07:07-0300",
      "stop_time": "Unknown"
    },
    {
      "id": "23844518666880373",
      "name": "mofu-contadores-tu-estudio-en-casa",
      "status": "PAUSED",
      "objective": "LINK_CLICKS",
      "created_time": "2020-04-07T11:56:18-0300",
      "updated_time": "2021-07-25T05:13:28-0300",
      "start_time": "2020-04-07T11:56:20-0300",
      "stop_time": "2020-04-30T15:46:36-0300"
    },
    {
      "id": "23844359586960373",
      "name": "Blog -\u00bfPor qu\u00e9 algunas empresas fracasan al contratar sistemas de gesti\u00f3n?",
      "status": "PAUSED",
      "objective": "LINK_CLICKS",
      "created_time": "2020-03-05T11:15:38-0300",
      "updated_time": "2022-02-15T11:25:42-0300",
      "start_time": "2020-03-05T11:15:41-0300",
      "stop_time": "2020-05-05T11:01:44-0300"
    },
    {
      "id": "23844103627900373",
      "name": "bofu-contadores-sueldos",
      "status": "PAUSED",
      "objective": "CONVERSIONS",
      "created_time": "2019-12-30T16:46:34-0300",
      "updated_time": "2020-08-07T15:53:20-0300",
      "start_time": "2019-12-30T16:46:36-0300",
      "stop_time": "Unknown"
    },
    {
      "id": "23843705809550373",
      "name": "pymes-mofu-facebook-factura-credito-electronica",
      "status": "PAUSED",
      "objective": "LINK_CLICKS",
      "created_time": "2019-09-11T14:37:10-0300",
      "updated_time": "2019-09-17T10:18:40-0300",
      "start_time": "2019-09-11T14:37:11-0300",
      "stop_time": "Unknown"
    },
    {
      "id": "23843634033040373",
      "name": "pymes-mofu-crm-zoho",
      "status": "PAUSED",
      "objective": "CONVERSIONS",
      "created_time": "2019-08-08T11:46:36-0300",
      "updated_time": "2019-08-08T16:40:02-0300",
      "start_time": "2019-08-08T11:46:37-0300",
      "stop_time": "Unknown"
    },
    {
      "id": "23843607019460373",
      "name": "mofu-pymes-ecommerce-vtex-tiendanube",
      "status": "PAUSED",
      "objective": "CONVERSIONS",
      "created_time": "2019-07-26T10:14:26-0300",
      "updated_time": "2019-08-08T16:42:53-0300",
      "start_time": "2019-07-26T10:14:28-0300",
      "stop_time": "Unknown"
    },
    {
      "id": "23843606963070373",
      "name": "mofu-pymes-ecommerce-mercadolibre",
      "status": "PAUSED",
      "objective": "CONVERSIONS",
      "created_time": "2019-07-26T09:10:25-0300",
      "updated_time": "2019-08-08T16:42:53-0300",
      "start_time": "2019-07-26T09:10:26-0300",
      "stop_time": "Unknown"
    },
    {
      "id": "23843605140490373",
      "name": "mofu-pymes-ecommerce",
      "status": "PAUSED",
      "objective": "CONVERSIONS",
      "created_time": "2019-07-25T14:02:10-0300",
      "updated_time": "2021-01-29T10:27:02-0300",
      "start_time": "2019-07-25T14:02:11-0300",
      "stop_time": "Unknown"
    },
    {
      "id": "23843599162740373",
      "name": "contadores-generica",
      "status": "PAUSED",
      "objective": "CONVERSIONS",
      "created_time": "2019-07-23T12:48:23-0300",
      "updated_time": "2021-01-29T10:27:03-0300",
      "start_time": "2019-07-23T12:48:25-0300",
      "stop_time": "Unknown"
    },
    {
      "id": "23843598973950373",
      "name": "mofu-contadores-conciliacion",
      "status": "PAUSED",
      "objective": "CONVERSIONS",
      "created_time": "2019-07-23T11:25:30-0300",
      "updated_time": "2019-08-08T16:42:53-0300",
      "start_time": "2019-07-23T11:25:31-0300",
      "stop_time": "Unknown"
    },
    {
      "id": "23843586621640373",
      "name": "Desayuno Factura de cr\u00e9dito electr\u00f3nica",
      "status": "PAUSED",
      "objective": "CONVERSIONS",
      "created_time": "2019-07-18T15:05:09-0300",
      "updated_time": "2021-07-24T23:03:45-0300",
      "start_time": "2019-07-18T16:00:16-0300",
      "stop_time": "2019-07-22T16:00:00-0300"
    },
    {
      "id": "23843578243300373",
      "name": "Desayuno \u00bfc\u00f3mo internacionalizar mi negocio?",
      "status": "PAUSED",
      "objective": "CONVERSIONS",
      "created_time": "2019-07-15T20:03:27-0300",
      "updated_time": "2021-07-24T22:41:27-0300",
      "start_time": "2019-07-15T20:30:57-0300",
      "stop_time": "2019-07-24T16:00:00-0300"
    },
    {
      "id": "23843578188380373",
      "name": "Desayuno: Conciliaci\u00f3n Bancaria",
      "status": "PAUSED",
      "objective": "LINK_CLICKS",
      "created_time": "2019-07-15T19:46:44-0300",
      "updated_time": "2021-07-24T22:41:27-0300",
      "start_time": "2019-07-16T06:00:22-0300",
      "stop_time": "2019-07-22T15:00:11-0300"
    },
    {
      "id": "23843520131310373",
      "name": "Desayuno: \u00bfQu\u00e9 son las SAS?",
      "status": "PAUSED",
      "objective": "LINK_CLICKS",
      "created_time": "2019-06-25T12:47:09-0300",
      "updated_time": "2021-07-24T22:18:24-0300",
      "start_time": "2019-06-25T12:47:11-0300",
      "stop_time": "2019-07-10T23:59:00-0300"
    },
    {
      "id": "23843509090680373",
      "name": "Desayuno: Aspectos Impositivos de Mercado Libre",
      "status": "PAUSED",
      "objective": "LINK_CLICKS",
      "created_time": "2019-06-21T12:39:32-0300",
      "updated_time": "2021-07-24T22:18:24-0300",
      "start_time": "2019-06-21T13:00:53-0300",
      "stop_time": "2019-06-26T12:00:53-0300"
    },
    {
      "id": "23843503545690373",
      "name": "Desayuno Mi Bucle",
      "status": "PAUSED",
      "objective": "LINK_CLICKS",
      "created_time": "2019-06-19T11:45:02-0300",
      "updated_time": "2021-07-24T22:18:24-0300",
      "start_time": "2019-06-19T12:30:47-0300",
      "stop_time": "2019-06-23T23:59:47-0300"
    },
    {
      "id": "23843472313300373",
      "name": "bofu-pymes-remarketing",
      "status": "PAUSED",
      "objective": "CONVERSIONS",
      "created_time": "2019-06-06T16:47:51-0300",
      "updated_time": "2019-08-08T16:45:53-0300",
      "start_time": "2019-06-06T16:47:52-0300",
      "stop_time": "Unknown"
    },
    {
      "id": "23843467655640373",
      "name": "bofu_pymes_interes",
      "status": "PAUSED",
      "objective": "CONVERSIONS",
      "created_time": "2019-06-04T17:24:55-0300",
      "updated_time": "2019-08-08T16:45:53-0300",
      "start_time": "2019-06-04T17:24:56-0300",
      "stop_time": "Unknown"
    },
    {
      "id": "23843467628550373",
      "name": "mofu_pymes_custom",
      "status": "PAUSED",
      "objective": "CONVERSIONS",
      "created_time": "2019-06-04T17:01:40-0300",
      "updated_time": "2019-08-08T16:45:53-0300",
      "start_time": "2019-06-04T17:01:42-0300",
      "stop_time": "Unknown"
    },
    {
      "id": "23843467240120373",
      "name": "mofu_pymes_lookalike",
      "status": "PAUSED",
      "objective": "CONVERSIONS",
      "created_time": "2019-06-04T13:10:39-0300",
      "updated_time": "2019-08-08T16:45:53-0300",
      "start_time": "2019-06-04T13:10:39-0300",
      "stop_time": "Unknown"
    },
    {
      "id": "23843467039190373",
      "name": "mofu-pymes-remarketing",
      "status": "PAUSED",
      "objective": "CONVERSIONS",
      "created_time": "2019-06-04T12:06:31-0300",
      "updated_time": "2019-08-08T16:45:53-0300",
      "start_time": "2019-06-04T12:06:32-0300",
      "stop_time": "Unknown"
    },
    {
      "id": "23843452346710373",
      "name": "tofu-mofu-pymes-pains-interes",
      "status": "PAUSED",
      "objective": "LINK_CLICKS",
      "created_time": "2019-06-04T09:58:05-0300",
      "updated_time": "2019-08-08T16:45:53-0300",
      "start_time": "2019-06-04T09:58:07-0300",
      "stop_time": "Unknown"
    },
    {
      "id": "23843425431410373",
      "name": "Desayuno 3 Ajuste Por Inflaci\u00f3n",
      "status": "PAUSED",
      "objective": "CONVERSIONS",
      "created_time": "2019-05-17T10:10:11-0300",
      "updated_time": "2021-07-24T21:42:58-0300",
      "start_time": "2019-05-17T10:10:13-0300",
      "stop_time": "2019-05-20T23:00:44-0300"
    },
    {
      "id": "23843421027390373",
      "name": "Promo-Mayo- Lookalike-custom",
      "status": "PAUSED",
      "objective": "LINK_CLICKS",
      "created_time": "2019-05-15T11:24:51-0300",
      "updated_time": "2021-07-24T21:42:58-0300",
      "start_time": "2019-05-15T11:24:53-0300",
      "stop_time": "2019-05-20T23:59:57-0300"
    },
    {
      "id": "23843421006670373",
      "name": "Promo-Mayo- Lookalike-web",
      "status": "PAUSED",
      "objective": "LINK_CLICKS",
      "created_time": "2019-05-15T11:11:02-0300",
      "updated_time": "2021-07-24T21:42:58-0300",
      "start_time": "2019-05-15T11:11:03-0300",
      "stop_time": "2019-05-20T23:59:57-0300"
    },
    {
      "id": "23843420930370373",
      "name": "Promo-Mayo-remarketing",
      "status": "PAUSED",
      "objective": "LINK_CLICKS",
      "created_time": "2019-05-15T10:27:51-0300",
      "updated_time": "2021-07-24T21:42:58-0300",
      "start_time": "2019-05-15T10:27:52-0300",
      "stop_time": "2019-05-20T23:59:57-0300"
    },
    {
      "id": "23843420883240373",
      "name": "Promo-Mayo-custom",
      "status": "PAUSED",
      "objective": "LINK_CLICKS",
      "created_time": "2019-05-15T09:57:13-0300",
      "updated_time": "2021-07-24T21:42:58-0300",
      "start_time": "2019-05-15T09:57:15-0300",
      "stop_time": "2019-05-20T23:59:57-0300"
    },
    {
      "id": "23843415592110373",
      "name": "Promo-Mayo",
      "status": "PAUSED",
      "objective": "LINK_CLICKS",
      "created_time": "2019-05-12T21:47:18-0300",
      "updated_time": "2021-07-24T21:42:58-0300",
      "start_time": "2019-05-13T00:00:57-0300",
      "stop_time": "2019-05-20T23:59:57-0300"
    },
    {
      "id": "23843384367150373",
      "name": "Desayuno 2 Ajuste Por Inflaci\u00f3n",
      "status": "PAUSED",
      "objective": "LINK_CLICKS",
      "created_time": "2019-04-25T18:51:42-0300",
      "updated_time": "2021-07-24T21:25:14-0300",
      "start_time": "2019-04-25T18:51:44-0300",
      "stop_time": "2019-04-28T23:00:20-0300"
    },
    {
      "id": "23843376922730373",
      "name": "DESAYUNO POTENCI\u00c1 TU ESTUDIO CONTABLE",
      "status": "PAUSED",
      "objective": "POST_ENGAGEMENT",
      "created_time": "2019-04-22T14:13:07-0300",
      "updated_time": "2021-07-24T21:25:14-0300",
      "start_time": "2019-04-22T14:45:56-0300",
      "stop_time": "2019-04-22T23:45:00-0300"
    },
    {
      "id": "23843358913200373",
      "name": "DESAYUNO AJUSTE POR INFLACI\u00d3N",
      "status": "PAUSED",
      "objective": "POST_ENGAGEMENT",
      "created_time": "2019-04-11T16:21:39-0300",
      "updated_time": "2021-07-24T21:13:55-0300",
      "start_time": "2019-04-11T16:21:46-0300",
      "stop_time": "2019-04-15T23:45:35-0300"
    },
    {
      "id": "23843327036830373",
      "name": "Webinar Integrando Salud - Marzo 2019",
      "status": "PAUSED",
      "objective": "LINK_CLICKS",
      "created_time": "2019-03-25T11:16:03-0300",
      "updated_time": "2021-07-24T20:52:15-0300",
      "start_time": "2019-03-25T11:16:04-0300",
      "stop_time": "2019-03-27T10:00:27-0300"
    },
    {
      "id": "23843319658000373",
      "name": "SUPER SALE MARZO 2019 CONTADORES",
      "status": "PAUSED",
      "objective": "CONVERSIONS",
      "created_time": "2019-03-20T11:33:47-0300",
      "updated_time": "2021-07-24T20:52:15-0300",
      "start_time": "2019-03-20T11:33:49-0300",
      "stop_time": "2019-03-31T17:00:38-0300"
    },
    {
      "id": "23843319591670373",
      "name": "SUPER SALE MARZO 2019 PYME",
      "status": "PAUSED",
      "objective": "CONVERSIONS",
      "created_time": "2019-03-20T10:47:44-0300",
      "updated_time": "2021-07-24T20:52:15-0300",
      "start_time": "2019-03-20T10:47:46-0300",
      "stop_time": "2019-03-31T17:00:38-0300"
    },
    {
      "id": "23843222386120373",
      "name": "Webinar Enero CTB",
      "status": "PAUSED",
      "objective": "LINK_CLICKS",
      "created_time": "2019-01-21T16:30:02-0300",
      "updated_time": "2021-07-24T19:38:02-0300",
      "start_time": "2019-01-21T16:30:03-0300",
      "stop_time": "2019-01-24T10:00:33-0300"
    },
    {
      "id": "23843203128530373",
      "name": "Buscando Contadores en CABA",
      "status": "PAUSED",
      "objective": "CONVERSIONS",
      "created_time": "2019-01-08T13:01:57-0300",
      "updated_time": "2019-04-26T17:52:41-0300",
      "start_time": "2019-01-08T13:01:59-0300",
      "stop_time": "Unknown"
    },
    {
      "id": "23843174765320373",
      "name": "CHRISTMAS SALE DICIEMBRE 2018",
      "status": "PAUSED",
      "objective": "CONVERSIONS",
      "created_time": "2018-12-17T17:02:17-0300",
      "updated_time": "2021-07-24T16:57:54-0300",
      "start_time": "2018-12-17T17:02:18-0300",
      "stop_time": "2018-12-30T17:30:37-0300"
    },
    {
      "id": "23843147203780373",
      "name": "Punto de Venta",
      "status": "PAUSED",
      "objective": "LINK_CLICKS",
      "created_time": "2018-11-29T11:02:30-0300",
      "updated_time": "2019-06-07T15:11:54-0300",
      "start_time": "2018-11-29T11:02:32-0300",
      "stop_time": "Unknown"
    },
    {
      "id": "23843145705490373",
      "name": "Merienda Contadores Diciembre",
      "status": "PAUSED",
      "objective": "LINK_CLICKS",
      "created_time": "2018-11-28T11:20:15-0300",
      "updated_time": "2021-07-16T07:52:54-0300",
      "start_time": "2018-11-28T11:20:16-0300",
      "stop_time": "2018-12-05T18:00:05-0300"
    },
    {
      "id": "23843110359100373",
      "name": "Webinar Pymes Noviembre",
      "status": "PAUSED",
      "objective": "LINK_CLICKS",
      "created_time": "2018-11-07T11:45:24-0300",
      "updated_time": "2021-07-16T07:09:37-0300",
      "start_time": "2018-11-07T12:00:09-0300",
      "stop_time": "2018-11-14T17:55:09-0300"
    },
    {
      "id": "23843093369040373",
      "name": "SUPER SALE OCTUBRE 2018",
      "status": "PAUSED",
      "objective": "CONVERSIONS",
      "created_time": "2018-10-28T13:12:38-0300",
      "updated_time": "2021-07-16T07:09:37-0300",
      "start_time": "2018-10-28T13:12:40-0300",
      "stop_time": "2018-10-31T17:00:00-0300"
    },
    {
      "id": "23843080991160373",
      "name": "Desayuno Contadores Octubre",
      "status": "PAUSED",
      "objective": "LINK_CLICKS",
      "created_time": "2018-10-19T16:58:13-0300",
      "updated_time": "2021-07-16T06:44:40-0300",
      "start_time": "2018-10-19T16:58:15-0300",
      "stop_time": "2018-10-24T17:00:37-0300"
    },
    {
      "id": "23843077867320373",
      "name": "Workshop Pymes Octubre",
      "status": "PAUSED",
      "objective": "LINK_CLICKS",
      "created_time": "2018-10-17T17:45:34-0300",
      "updated_time": "2021-07-16T06:44:40-0300",
      "start_time": "2018-10-17T17:45:35-0300",
      "stop_time": "2018-10-29T17:45:11-0300"
    },
    {
      "id": "23843060460140373",
      "name": "Workshop Contadores Octubre",
      "status": "PAUSED",
      "objective": "LINK_CLICKS",
      "created_time": "2018-10-04T17:34:32-0300",
      "updated_time": "2021-07-16T06:07:31-0300",
      "start_time": "2018-10-04T17:34:33-0300",
      "stop_time": "2018-10-10T18:00:10-0300"
    },
    {
      "id": "23843009224370373",
      "name": "Funcionalidades Colppy 2",
      "status": "PAUSED",
      "objective": "LINK_CLICKS",
      "created_time": "2018-08-28T14:17:57-0300",
      "updated_time": "2021-07-16T03:47:10-0300",
      "start_time": "2018-09-01T13:42:55-0300",
      "stop_time": "2018-12-31T13:42:55-0300"
    },
    {
      "id": "23843003295880373",
      "name": "Funcionalidades Colppy",
      "status": "PAUSED",
      "objective": "CONVERSIONS",
      "created_time": "2018-08-24T11:48:56-0300",
      "updated_time": "2021-07-16T03:47:10-0300",
      "start_time": "2018-08-25T16:39:46-0300",
      "stop_time": "2018-08-31T16:39:46-0300"
    },
    {
      "id": "23842955402660373",
      "name": "Leads Manejo Administrativo Blog",
      "status": "PAUSED",
      "objective": "LEAD_GENERATION",
      "created_time": "2018-07-17T12:50:21-0300",
      "updated_time": "2021-07-16T02:29:11-0300",
      "start_time": "2018-07-17T14:30:39-0300",
      "stop_time": "2018-12-31T12:08:39-0300"
    },
    {
      "id": "23842950575910373",
      "name": "Leads Cadena de Pagos",
      "status": "PAUSED",
      "objective": "LEAD_GENERATION",
      "created_time": "2018-07-12T17:54:45-0300",
      "updated_time": "2021-07-16T01:56:47-0300",
      "start_time": "2018-07-12T17:54:48-0300",
      "stop_time": "2018-12-31T18:00:51-0300"
    },
    {
      "id": "23842949102030373",
      "name": "Tr\u00e1fico Emprendedor Blog",
      "status": "PAUSED",
      "objective": "LINK_CLICKS",
      "created_time": "2018-07-11T15:41:17-0300",
      "updated_time": "2021-07-16T01:56:47-0300",
      "start_time": "2018-07-11T15:41:19-0300",
      "stop_time": "2018-12-31T15:28:54-0300"
    },
    {
      "id": "23842889984550373",
      "name": "Promo descuento fin de mes - Copia",
      "status": "PAUSED",
      "objective": "CONVERSIONS",
      "created_time": "2018-05-28T16:42:58-0300",
      "updated_time": "2018-07-02T10:44:01-0300",
      "start_time": "2018-05-28T16:42:59-0300",
      "stop_time": "Unknown"
    },
    {
      "id": "23842878135360373",
      "name": "Programa de Referidos",
      "status": "PAUSED",
      "objective": "CONVERSIONS",
      "created_time": "2018-05-18T17:22:42-0300",
      "updated_time": "2018-05-28T14:46:01-0300",
      "start_time": "2018-05-18T17:22:42-0300",
      "stop_time": "Unknown"
    },
    {
      "id": "23842873810930373",
      "name": "HOT SALE MAYO",
      "status": "PAUSED",
      "objective": "CONVERSIONS",
      "created_time": "2018-05-15T10:41:12-0300",
      "updated_time": "2018-05-21T10:27:04-0300",
      "start_time": "2018-05-15T10:41:12-0300",
      "stop_time": "Unknown"
    },
    {
      "id": "23842873810500373",
      "name": "HOT SALE MAYO",
      "status": "PAUSED",
      "objective": "CONVERSIONS",
      "created_time": "2018-05-15T10:40:12-0300",
      "updated_time": "2018-05-18T16:34:25-0300",
      "start_time": "1969-12-31T20:59:59-0300",
      "stop_time": "Unknown"
    },
    {
      "id": "23842869440010373",
      "name": "Display Contadores",
      "status": "PAUSED",
      "objective": "CONVERSIONS",
      "created_time": "2018-05-11T12:33:46-0300",
      "updated_time": "2018-07-18T11:21:38-0300",
      "start_time": "2018-05-11T12:33:47-0300",
      "stop_time": "Unknown"
    },
    {
      "id": "23842845969410373",
      "name": "Promo descuento fin de mes",
      "status": "PAUSED",
      "objective": "CONVERSIONS",
      "created_time": "2018-04-25T14:52:49-0300",
      "updated_time": "2021-07-16T00:31:42-0300",
      "start_time": "2018-04-25T14:52:50-0300",
      "stop_time": "2018-08-31T18:00:14-0300"
    },
    {
      "id": "23842795845760373",
      "name": "Conciliacion Bancaria ",
      "status": "PAUSED",
      "objective": "LINK_CLICKS",
      "created_time": "2018-03-20T18:05:37-0300",
      "updated_time": "2019-04-19T21:45:46-0300",
      "start_time": "2018-03-20T18:05:37-0300",
      "stop_time": "Unknown"
    },
    {
      "id": "23842784910190373",
      "name": "Ebook",
      "status": "PAUSED",
      "objective": "CONVERSIONS",
      "created_time": "2018-03-08T13:49:59-0300",
      "updated_time": "2018-12-31T10:33:56-0300",
      "start_time": "2018-03-08T13:49:59-0300",
      "stop_time": "Unknown"
    },
    {
      "id": "23842779323880373",
      "name": "Mercado Pago",
      "status": "PAUSED",
      "objective": "LINK_CLICKS",
      "created_time": "2018-03-02T16:14:23-0300",
      "updated_time": "2019-04-19T21:58:30-0300",
      "start_time": "2018-03-02T16:14:25-0300",
      "stop_time": "Unknown"
    },
    {
      "id": "23842766374600373",
      "name": "Promo fin de Febrero",
      "status": "PAUSED",
      "objective": "CONVERSIONS",
      "created_time": "2018-02-19T14:54:23-0300",
      "updated_time": "2021-07-15T21:29:13-0300",
      "start_time": "2018-02-19T14:54:24-0300",
      "stop_time": "2018-02-28T19:00:24-0300"
    },
    {
      "id": "23842729954800373",
      "name": "Gesti\u00f3n Pymes AR",
      "status": "PAUSED",
      "objective": "CONVERSIONS",
      "created_time": "2018-01-08T15:20:51-0300",
      "updated_time": "2019-06-06T15:18:47-0300",
      "start_time": "2018-01-08T15:20:51-0300",
      "stop_time": "Unknown"
    },
    {
      "id": "23842729947180373",
      "name": "Gesti\u00f3n Emprendedores",
      "status": "PAUSED",
      "objective": "POST_ENGAGEMENT",
      "created_time": "2018-01-08T15:13:03-0300",
      "updated_time": "2022-10-06T11:30:37-0300",
      "start_time": "2018-01-08T15:13:05-0300",
      "stop_time": "Unknown"
    },
    {
      "id": "23842729932760373",
      "name": "Facturaci\u00f3n",
      "status": "PAUSED",
      "objective": "CONVERSIONS",
      "created_time": "2018-01-08T14:54:37-0300",
      "updated_time": "2022-11-02T14:50:55-0300",
      "start_time": "2018-01-08T14:54:39-0300",
      "stop_time": "Unknown"
    }
  ],
  "summary": {
    "total_campaigns": 179,
    "active_campaigns": 1,
    "paused_campaigns": 178,
    "analysis_date": "2025-09-10T13:53:17.914455"
  }
}